polytracker/__init__.py
polytracker/__main__.py
polytracker/build.py
polytracker/cache.py
polytracker/cfg.py
polytracker/containerization.py
polytracker/database.py
polytracker/datalog.py
polytracker/diffing.py
polytracker/grammars.py
polytracker/graphs.py
polytracker/inputs.py
polytracker/mapping.py
polytracker/parsing.py
polytracker/plugins.py
polytracker/polytracker.py
polytracker/repl.py
polytracker/taint_dag.py
polytracker/taint_forest.py
polytracker/tracing.py
polytracker/visualizations.py
tests/__init__.py
tests/conftest.py
tests/data.py
tests/test_argv.py
tests/test_bb_splitting.py
tests/test_cache.py
tests/test_db.py
tests/test_grammar_extraction_native.py
tests/test_grammar_extraction_python.py
tests/test_plugins.py
tests/test_polytracker.py
tests/test_stdio.py
tests/test_tdag.py
tests/tracing.py
polytracker-4.0.0.dist-info/LICENSE
polytracker-4.0.0.dist-info/METADATA
polytracker-4.0.0.dist-info/WHEEL
polytracker-4.0.0.dist-info/entry_points.txt
polytracker-4.0.0.dist-info/top_level.txt
polytracker-4.0.0.dist-info/RECORD
