Metadata-Version: 2.1
Name: polytracker
Version: 4.0.0
Summary: An LLVM-based instrumentation tool for universal taint tracking, dataflow analysis, and tracing.
Home-page: https://github.com/trailofbits/polytracker
Author: Trail of Bits
Classifier: Development Status :: 4 - Beta
Classifier: Environment :: Console
Classifier: Intended Audience :: Science/Research
Classifier: License :: OSI Approved :: Apache Software License
Classifier: Programming Language :: Python :: 3 :: Only
Classifier: Topic :: Utilities
Requires-Python: >=3.7
License-File: LICENSE
Requires-Dist: blight (~=0.0.47)
Requires-Dist: cxxfilt (~=0.2.2)
Requires-Dist: docker (~=4.4.0)
Requires-Dist: graphviz (~=0.14.1)
Requires-Dist: intervaltree (~=3.0.2)
Requires-Dist: matplotlib (~=3.3.0)
Requires-Dist: networkx (~=2.4)
Requires-Dist: Pillow (>=7.2.0)
Requires-Dist: prompt-toolkit (~=3.0.8)
Requires-Dist: pygments (~=2.7.3)
Requires-Dist: pydot (~=1.4.1)
Requires-Dist: sqlalchemy (~=1.3.23)
Requires-Dist: tqdm (>=4.59.0)
Requires-Dist: typing-extensions (>=3.7.4.2)
Requires-Dist: types-setuptools (~=57.4.9)
Provides-Extra: dev
Requires-Dist: black (>=20.8b1) ; extra == 'dev'
Requires-Dist: mypy ; extra == 'dev'
Requires-Dist: pytest ; extra == 'dev'
Requires-Dist: flake8 ; extra == 'dev'
Requires-Dist: Sphinx ; extra == 'dev'
Requires-Dist: sphinx-rtd-theme (~=0.4.3) ; extra == 'dev'
Requires-Dist: types-setuptools ; extra == 'dev'
